debian/changelog
reahl-browsertools/reahl/browsertools/__init__.py
reahl-browsertools/reahl/browsertools/browsertools.py
reahl-browsertools/reahl/browsertools_dev/__init__.py
reahl-commands/.reahlalias
reahl-commands/README.rst
reahl-commands/pyproject.toml
reahl-commands/tox.ini
reahl-commands/reahl/commands/__init__.py
reahl-commands/reahl/commands/migrations.py
reahl-commands/reahl/commands/prodshell.py
reahl-component/conftest.py
reahl-component/etc/reahl.config.py
reahl-component/reahl/component/__init__.py
reahl-component/reahl/component/config.py
reahl-component/reahl/component/context.py
reahl-component/reahl/component/dbutils.py
reahl-component/reahl/component/decorators.py
reahl-component/reahl/component/eggs.py
reahl-component/reahl/component/exceptions.py
reahl-component/reahl/component/i18n.py
reahl-component/reahl/component/migration.py
reahl-component/reahl/component/modelinterface.py
reahl-component/reahl/component/shelltools.py
reahl-component/reahl/component_dev/__init__.py
reahl-component/reahl/component_dev/test_argumentchecks.py
reahl-component/reahl/component_dev/test_component.py
reahl-component/reahl/component_dev/test_config.py
reahl-component/reahl/component_dev/test_context.py
reahl-component/reahl/component_dev/test_dbutils.py
reahl-component/reahl/component_dev/test_decorators.py
reahl-component/reahl/component_dev/test_domainaccesscontrol.py
reahl-component/reahl/component_dev/test_field.py
reahl-component/reahl/component_dev/test_i18n.py
reahl-component/reahl/component_dev/test_migration.py
reahl-component-metadata/.reahlalias
reahl-component-metadata/README.rst
reahl-component-metadata/pyproject.toml
reahl-component-metadata/tox.ini
reahl-component-metadata/build/lib/reahl/componentmetadata/__init__.py
reahl-component-metadata/build/lib/reahl/componentmetadata/setuptools.py
reahl-component-metadata/reahl/componentmetadata/__init__.py
reahl-component-metadata/reahl/componentmetadata/setuptools.py
reahl-dev/conftest.py
reahl-7.0.3.dist-info/LICENSE.reahl
reahl-7.0.3.dist-info/LICENSE.reahl-browsertools
reahl-7.0.3.dist-info/LICENSE.reahl-component
reahl-7.0.3.dist-info/LICENSE.reahl-dev
reahl-7.0.3.dist-info/LICENSE.reahl-doc
reahl-7.0.3.dist-info/LICENSE.reahl-domain
reahl-7.0.3.dist-info/LICENSE.reahl-domainui
reahl-7.0.3.dist-info/LICENSE.reahl-mailutil
reahl-7.0.3.dist-info/LICENSE.reahl-mysqlsupport
reahl-7.0.3.dist-info/LICENSE.reahl-paypalsupport
reahl-7.0.3.dist-info/LICENSE.reahl-postgresqlsupport
reahl-7.0.3.dist-info/LICENSE.reahl-sqlalchemysupport
reahl-7.0.3.dist-info/LICENSE.reahl-sqlitesupport
reahl-7.0.3.dist-info/LICENSE.reahl-stubble
reahl-7.0.3.dist-info/LICENSE.reahl-tofu
reahl-7.0.3.dist-info/LICENSE.reahl-web
reahl-7.0.3.dist-info/LICENSE.reahl-web-declarative
reahl-7.0.3.dist-info/LICENSE.reahl-webdev
reahl-7.0.3.dist-info/LICENSE.reahl-workstation
reahl-7.0.3.dist-info/METADATA
reahl-7.0.3.dist-info/WHEEL
reahl-7.0.3.dist-info/top_level.txt
reahl-7.0.3.dist-info/RECORD
