Metadata-Version: 2.1
Name: reahl
Version: 7.0.3
Summary: The Reahl web framework.
Author-email: Iwan Vosloo <iwan@reahl.org>, Craig Sparks <craig@reahl.org>
Classifier: Development Status :: 5 - Production/Stable
Classifier: Intended Audience :: Developers
Classifier: License :: OSI Approved
Classifier: Operating System :: OS Independent
Classifier: Programming Language :: Python :: 3
Requires-Python: >=3.8
License-File: LICENSE.reahl
License-File: LICENSE.reahl-browsertools
License-File: LICENSE.reahl-component
License-File: LICENSE.reahl-dev
License-File: LICENSE.reahl-doc
License-File: LICENSE.reahl-domain
License-File: LICENSE.reahl-domainui
License-File: LICENSE.reahl-mailutil
License-File: LICENSE.reahl-mysqlsupport
License-File: LICENSE.reahl-paypalsupport
License-File: LICENSE.reahl-postgresqlsupport
License-File: LICENSE.reahl-sqlalchemysupport
License-File: LICENSE.reahl-sqlitesupport
License-File: LICENSE.reahl-stubble
License-File: LICENSE.reahl-tofu
License-File: LICENSE.reahl-web
License-File: LICENSE.reahl-web-declarative
License-File: LICENSE.reahl-webdev
License-File: LICENSE.reahl-workstation
Provides-Extra: all
Requires-Dist: reahl-component <7.1,>=7.0 ; extra == 'all'
Requires-Dist: reahl-web <7.1,>=7.0 ; extra == 'all'
Requires-Dist: reahl-mailutil <7.1,>=7.0 ; extra == 'all'
Requires-Dist: reahl-sqlalchemysupport <7.1,>=7.0 ; extra == 'all'
Requires-Dist: reahl-web-declarative <7.1,>=7.0 ; extra == 'all'
Requires-Dist: reahl-domain <7.1,>=7.0 ; extra == 'all'
Requires-Dist: reahl-domainui <7.1,>=7.0 ; extra == 'all'
Requires-Dist: reahl-postgresqlsupport <7.1,>=7.0 ; extra == 'all'
Requires-Dist: reahl-sqlitesupport <7.1,>=7.0 ; extra == 'all'
Requires-Dist: reahl-mysqlsupport <7.1,>=7.0 ; extra == 'all'
Requires-Dist: reahl-dev <7.1,>=7.0 ; extra == 'all'
Requires-Dist: reahl-webdev <7.1,>=7.0 ; extra == 'all'
Requires-Dist: reahl-browsertools <7.1,>=7.0 ; extra == 'all'
Requires-Dist: reahl-stubble <7.1,>=7.0 ; extra == 'all'
Requires-Dist: reahl-tofu <7.1,>=7.0 ; extra == 'all'
Requires-Dist: reahl-doc <7.1,>=7.0 ; extra == 'all'
Requires-Dist: reahl-commands <7.1,>=7.0 ; extra == 'all'
Requires-Dist: reahl-paypalsupport <7.1,>=7.0 ; extra == 'all'
Provides-Extra: browsertools
Requires-Dist: reahl-browsertools <7.1,>=7.0 ; extra == 'browsertools'
Provides-Extra: component
Requires-Dist: reahl-component <7.1,>=7.0 ; extra == 'component'
Provides-Extra: declarative
Requires-Dist: reahl-sqlalchemysupport <7.1,>=7.0 ; extra == 'declarative'
Requires-Dist: reahl-web-declarative <7.1,>=7.0 ; extra == 'declarative'
Requires-Dist: reahl-domain <7.1,>=7.0 ; extra == 'declarative'
Requires-Dist: reahl-domainui <7.1,>=7.0 ; extra == 'declarative'
Provides-Extra: dev
Requires-Dist: reahl-dev <7.1,>=7.0 ; extra == 'dev'
Requires-Dist: reahl-webdev <7.1,>=7.0 ; extra == 'dev'
Requires-Dist: reahl-stubble <7.1,>=7.0 ; extra == 'dev'
Requires-Dist: reahl-tofu <7.1,>=7.0 ; extra == 'dev'
Requires-Dist: reahl-browsertools <7.1,>=7.0 ; extra == 'dev'
Provides-Extra: doc
Requires-Dist: reahl-doc <7.1,>=7.0 ; extra == 'doc'
Provides-Extra: mysql
Requires-Dist: reahl-mysqlsupport <7.1,>=7.0 ; extra == 'mysql'
Provides-Extra: postgresql
Requires-Dist: reahl-postgresqlsupport <7.1,>=7.0 ; extra == 'postgresql'
Provides-Extra: sqlite
Requires-Dist: reahl-sqlitesupport <7.1,>=7.0 ; extra == 'sqlite'
Provides-Extra: stubble
Requires-Dist: reahl-stubble <7.1,>=7.0 ; extra == 'stubble'
Provides-Extra: tofu
Requires-Dist: reahl-tofu <7.1,>=7.0 ; extra == 'tofu'
Provides-Extra: web
Requires-Dist: reahl-component <7.1,>=7.0 ; extra == 'web'
Requires-Dist: reahl-web <7.1,>=7.0 ; extra == 'web'
Requires-Dist: reahl-mailutil <7.1,>=7.0 ; extra == 'web'
